genice2_rdf/__init__.py
genice2_rdf/formats/_RDF.py
genice2_rdf/formats/__init__.py
genice2_rdf-2.1.dist-info/METADATA
genice2_rdf-2.1.dist-info/WHEEL
genice2_rdf-2.1.dist-info/entry_points.txt
genice2_rdf-2.1.dist-info/top_level.txt
genice2_rdf-2.1.dist-info/RECORD
