Metadata-Version: 2.1
Name: genice2-rdf
Version: 2.1
Summary: RDF format plugin for GenIce.
Home-page: https://github.com/vitroid/genice-rdf/
Author: Masakazu Matsumoto
Author-email: vitroid@gmail.com
License: MIT
Keywords: genice,RDF
Platform: UNKNOWN
Classifier: Development Status :: 4 - Beta
Classifier: Intended Audience :: Developers
Classifier: Programming Language :: Python
Classifier: Programming Language :: Python :: 3.6
Requires-Dist: PairList (>=0.2.11.1)
Requires-Dist: GenIce2 (>=2.1b2)
